odoo/addons/sale_order_tag/README.rst
odoo/addons/sale_order_tag/__init__.py
odoo/addons/sale_order_tag/__manifest__.py
odoo/addons/sale_order_tag/data/sale_order_tag_data.xml
odoo/addons/sale_order_tag/i18n/ca.po
odoo/addons/sale_order_tag/i18n/de.po
odoo/addons/sale_order_tag/i18n/es.po
odoo/addons/sale_order_tag/i18n/it.po
odoo/addons/sale_order_tag/i18n/pt.po
odoo/addons/sale_order_tag/i18n/sale_order_tag.pot
odoo/addons/sale_order_tag/i18n/tr.po
odoo/addons/sale_order_tag/models/__init__.py
odoo/addons/sale_order_tag/models/sale_order.py
odoo/addons/sale_order_tag/models/sale_order_tag.py
odoo/addons/sale_order_tag/readme/CONTRIBUTORS.md
odoo/addons/sale_order_tag/readme/DESCRIPTION.md
odoo/addons/sale_order_tag/readme/USAGE.md
odoo/addons/sale_order_tag/security/ir.model.access.csv
odoo/addons/sale_order_tag/security/sale_order_tag_security.xml
odoo/addons/sale_order_tag/static/description/icon.png
odoo/addons/sale_order_tag/static/description/index.html
odoo/addons/sale_order_tag/views/sale_order.xml
odoo/addons/sale_order_tag/views/sale_order_tag.xml
odoo_addon_sale_order_tag-18.0.1.0.0.4.dist-info/METADATA
odoo_addon_sale_order_tag-18.0.1.0.0.4.dist-info/WHEEL
odoo_addon_sale_order_tag-18.0.1.0.0.4.dist-info/top_level.txt
odoo_addon_sale_order_tag-18.0.1.0.0.4.dist-info/RECORD
